LICENSE.txt
README.txt
setup.cfg
setup.py
TGFastData.egg-info/PKG-INFO
TGFastData.egg-info/SOURCES.txt
TGFastData.egg-info/dependency_links.txt
TGFastData.egg-info/entry_points.txt
TGFastData.egg-info/not-zip-safe
TGFastData.egg-info/requires.txt
TGFastData.egg-info/top_level.txt
tgfastdata/__init__.py
tgfastdata/datacontroller.py
tgfastdata/datawidgets.py
tgfastdata/formmaker.py
tgfastdata/plugin.py
tgfastdata/release.py
tgfastdata/templates/__init__.py
tgfastdata/templates/datagrid.kid
tgfastdata/templates/editform.kid
tgfastdata/templates/form.kid
tgfastdata/templates/item.kid
tgfastdata/templates/list.kid
tgfastdata/templates/master.kid
tgfastdata/tests/__init__.py
tgfastdata/tests/formmodel.py
tgfastdata/tests/test_datacontroller.py
tgfastdata/tests/test_fastdata.py
tgfastdata/tests/test_formmaker.py
