Metadata-Version: 1.0
Name: TGFastData
Version: 0.9a7
Summary: Automatic user interface generation for TurboGears
Home-page: http://www.turbogears.org
Author: Kevin Dangoor
Author-email: dangoor+turbogears@gmail.com
License: MIT
Download-URL: http://www.turbogears.org/download/
Platform: UNKNOWN
Classifier: Development Status :: 3 - Alpha
Classifier: Environment :: Console
Classifier: Intended Audience :: Developers
Classifier: License :: OSI Approved :: MIT License
Classifier: Operating System :: OS Independent
Classifier: Programming Language :: Python
Classifier: Topic :: Software Development :: Libraries :: Python Modules
